__init__.py
scrapeTiger.py
scrapeTiger-1.0.4.dist-info/LICENSE.txt
scrapeTiger-1.0.4.dist-info/METADATA
scrapeTiger-1.0.4.dist-info/WHEEL
scrapeTiger-1.0.4.dist-info/top_level.txt
scrapeTiger-1.0.4.dist-info/RECORD
