Metadata-Version: 2.1
Name: scrapeTiger
Version: 1.0.4
Summary: scrapeTiger is an python package for web scraping.
Author-email: FARHAN AHMED <contact@farhyn.com>
Project-URL: Homepage, https://github.com/MDFARHYN/scrapeTiger
Project-URL: Bug Tracker, https://github.com/MDFARHYN/scrapeLion/scrapeTiger
Keywords: web scraping,data mining,scraping tools,scraping tiger,farhyn.com
Classifier: Programming Language :: Python :: 3
Classifier: License :: OSI Approved :: MIT License
Classifier: Operating System :: OS Independent
Requires-Python: >=3.7
License-File: LICENSE.txt
Requires-Dist: selenium
Requires-Dist: webdriver-manager
